Py3ComUtils/Codec.py
Py3ComUtils/Decrypt.py
Py3ComUtils/FileHandler.py
Py3ComUtils/__init__.py
Py3ComUtils-1.0.5.dist-info/LICENSE
Py3ComUtils-1.0.5.dist-info/METADATA
Py3ComUtils-1.0.5.dist-info/WHEEL
Py3ComUtils-1.0.5.dist-info/top_level.txt
Py3ComUtils-1.0.5.dist-info/RECORD
