Metadata-Version: 2.1
Name: Py3ComUtils
Version: 1.0.5
Summary: A collection of commonly used utility functions for Python 3
Home-page: https://github.com/Rin-Wood/Py3ComUtils
Author: wood
Author-email: miraclerinwood@gmail.com
License: MIT
Keywords: utilities,Python,common functions,Py3ComUtils
Classifier: Development Status :: 5 - Production/Stable
Classifier: Intended Audience :: Developers
Classifier: License :: OSI Approved :: MIT License
Classifier: Operating System :: OS Independent
Classifier: Programming Language :: Python
Classifier: Programming Language :: Python :: 3
Classifier: Programming Language :: Python :: 3.6
Classifier: Programming Language :: Python :: 3.7
Classifier: Programming Language :: Python :: 3.8
Classifier: Programming Language :: Python :: 3.9
Classifier: Programming Language :: Python :: 3.10
Classifier: Programming Language :: Python :: 3.11
Classifier: Programming Language :: Python :: 3.12
Classifier: Programming Language :: Python :: 3.13
Requires-Python: >=3.6
License-File: LICENSE
Requires-Dist: bbpb
Requires-Dist: brotli
Requires-Dist: lz4
Requires-Dist: msgpack
Requires-Dist: numpy
Requires-Dist: Pillow
Requires-Dist: pycryptodome
Requires-Dist: texture2ddecoder
Requires-Dist: xmltodict
Requires-Dist: cxxtea
Requires-Dist: crijndael
